metasay/__init__.py
metasay/scripts/__init__.py
metasay/scripts/cli.py
rio_metasay-1.2.0.dist-info/DESCRIPTION.rst
rio_metasay-1.2.0.dist-info/entry_points.txt
rio_metasay-1.2.0.dist-info/METADATA
rio_metasay-1.2.0.dist-info/metadata.json
rio_metasay-1.2.0.dist-info/RECORD
rio_metasay-1.2.0.dist-info/top_level.txt
rio_metasay-1.2.0.dist-info/WHEEL
