Metadata-Version: 2.0
Name: rio-metasay
Version: 1.2.0
Summary: Skeleton of a Python package
Home-page: https://github.com/sgillies/rio-plugin-example
Author: Sean Gillies
Author-email: sean.gillies@gmail.com
License: BSD
Platform: UNKNOWN
Requires-Dist: click
Requires-Dist: cowpy
Requires-Dist: rasterio
Provides-Extra: test
Requires-Dist: pytest; extra == 'test'
